rex/__init__.py
rex/actor_critic.py
rex/artificial.py
rex/asynchronous.py
rex/base.py
rex/cem.py
rex/constants.py
rex/evo.py
rex/gmm_estimator.py
rex/graph.py
rex/jax_utils.py
rex/node.py
rex/open_colors.py
rex/partition_runner.py
rex/ppo.py
rex/rl.py
rex/utils.py
rex/examples/__init__.py
rex/examples/pendulum/__init__.py
rex/examples/pendulum/actuator.py
rex/examples/pendulum/agent.py
rex/examples/pendulum/brax.py
rex/examples/pendulum/ode.py
rex/examples/pendulum/render.py
rex/examples/pendulum/rl.py
rex/examples/pendulum/sensor.py
rex_lib-0.0.12.dist-info/METADATA
rex_lib-0.0.12.dist-info/WHEEL
rex_lib-0.0.12.dist-info/licenses/LICENSE
rex_lib-0.0.12.dist-info/RECORD
