Metadata-Version: 2.4
Name: rex-lib
Version: 0.0.12
Summary: Robotic Environments with jaX (REX)
Author-email: Bas van der Heijden <b.heijden@hotmail.com>
License:                                  Apache License
License-File: LICENSE
Keywords: jax,reinforcement-learning,robotics,sim2real,simulation
Classifier: License :: OSI Approved :: Apache Software License
Classifier: Operating System :: OS Independent
Classifier: Programming Language :: Python :: 3
Classifier: Programming Language :: Python :: 3.9
Classifier: Programming Language :: Python :: 3.10
Classifier: Programming Language :: Python :: 3.11
Requires-Python: >=3.9
Requires-Dist: distrax>=0.1.5
Requires-Dist: equinox>=0.11.4
Requires-Dist: evosax<0.2.0,>=0.1.6
Requires-Dist: flax>=0.8.5
Requires-Dist: jax>=0.4.30
Requires-Dist: matplotlib>=3.7.0
Requires-Dist: networkx>=3.2.1
Requires-Dist: optax>=0.2.3
Requires-Dist: supergraph>=0.0.8
Requires-Dist: tqdm>=4.66.4
Provides-Extra: examples
Requires-Dist: brax>=0.12.0; extra == 'examples'
Requires-Dist: dill>=0.3.8; extra == 'examples'
Requires-Dist: ipykernel>=6.29.5; extra == 'examples'
Requires-Dist: jupyterlab>=4.3.2; extra == 'examples'
Requires-Dist: seaborn>=0.13.2; extra == 'examples'
